ldmud_tracing/__init__.py
ldmud_tracing/formatting.py
ldmud_tracing/profile.py
ldmud_tracing/tracing.py
ldmud_tracing-0.0.2.dist-info/LICENSE
ldmud_tracing-0.0.2.dist-info/METADATA
ldmud_tracing-0.0.2.dist-info/WHEEL
ldmud_tracing-0.0.2.dist-info/entry_points.txt
ldmud_tracing-0.0.2.dist-info/top_level.txt
ldmud_tracing-0.0.2.dist-info/RECORD
