Metadata-Version: 2.1
Name: ldmud-tracing
Version: 0.0.2
Summary: Python tracing package for LDMud
Home-page: https://github.com/ldmud/python-dbus
Author: LDMud Team
Author-email: ldmud-dev@UNItopia.DE
Classifier: Programming Language :: Python :: 3
Classifier: Operating System :: OS Independent
License-File: LICENSE
